project2/Final/PartD/baud_controller.v
module baud_controller (reset, clk, baud_select, Tx_EN, sample_ENABLE);
    
    input clk, reset; //clk should be default 100MHz clock on baudrate controller
    input [2:0] baud_select;
    input Tx_EN;
    output reg sample_ENABLE; //active on positive, should remain active for a cycle

    reg [14:0] counter, countMax;

    //Put in separate always to avoid z post-synthesis
    always @(baud_select) begin
        case (baud_select)
            3'b000: countMax = 15'b101000101100001; //20833
            3'b001: countMax = 15'b001010001011000; // 5208
            3'b010: countMax = 15'b000010100010111; // 1303
            3'b011: countMax = 15'b000001010001011; //  651
            3'b100: countMax = 15'b000000101000110; //  326
            3'b101: countMax = 15'b000000010100011; //  163
            3'b110: countMax = 15'b000000001101101; //  109
            3'b111: countMax = 15'b000000000110110; //   54
            default: countMax = 15'b000000000000000;//    0

        endcase
    end

    always @(posedge clk or posedge reset) begin
        if(reset)begin
            counter <= 0;
            sample_ENABLE <= 0;
        end
        else begin
            //No need to run if transmitter/receiver off
            if(Tx_EN == 0)begin
                counter <= 0; 
                sample_ENABLE <= 0;
            end
            //sample_ENABLE on countMax
            else if(counter == countMax) begin
                counter <= 0;
                sample_ENABLE <= 1;
            end
            else begin
                counter <= counter + 1;
                sample_ENABLE <= 0;
            end
        end
    end

endmodule

/* Sampling Periods For Baud Rate:
 * = 300:    1/(16*300)    = 2.0833333...*10^(-4)
 *           /clk_period   = 20833.333...
 *                         = 15'b101000101100001 
 *
 * = 1200:   1/(16*1200)   = 5.20833333...*10^(-5)
 *           /clk_period   = 5208.33333...
 *                         = 13'b1010001011000
 *
 * = 4800:   1/(16*4800)   = 1.302833333...*10^(-5)
 *           /clk_period   = 1302.833333...
 *                         = 11'b10100010111
 *
 * = 9600:   1/(16*9600)   = 6.5104166666...*10^(-6)
 *           /clk_period   = 651.04166666...
 *                         = 10'b1010001100
 *
 * = 19200:  1/(16*19200)  = 3.25520833333...*10^(-6)
 *           /clk_period   = 325.520833333...
 *                         = 9'b101000110
 *
 * = 38400:  1/(16*38400)  = 1.627604166666...*10^(-6)
 *           /clk_period   = 162.7604166666...
 *                         = 8'b10100011
 *
 * = 57600:  1/(16*57600)  = 1.08506944444...*10^(-6)
 *           /clk_period   = 108.506944444...
 *                         = 7'b1101101
 *
 * = 115200: 1/(16*115200) = 5.42534722222...*10^(-7)
 *           /clk_period   = 54.2534722222...
 *                         = 6'b110110
 *
 * Above period is in seconds
 * Note: 1ns = 10^(-9)s
 *       input clock frequency = 100MHz
 *       ...         period = 10^(-8)
 * Note: decimals are rounded before conversion
 *
**/

project2/Working/PartB/verilog/baud_controller_tb.v
`timescale 1ns/10ps

module baud_controller_tb;

    reg clk, reset, EN;
    reg [2:0] baud_select;
    wire sample_ENABLE;

    baud_controller baud_controller_bench(reset, clk, baud_select, EN, sample_ENABLE);

    initial begin
        $dumpfile("baud_controller_tb.vcd");
        $dumpvars(0, baud_controller_tb);

        clk = 0;
        reset = 1;
        baud_select = 7;
        EN = 1;

        #5 reset = 1;
        #20 reset = 0;

        #18000 $finish;
    end
    initial begin
        forever begin
            #5 clk = ~clk;
        end
    end
    initial begin
        forever begin
            #3000 baud_select = baud_select - 1;
            #5 reset = 1;
            #20 reset = 0;
        end
    end
endmodule

project2/Working/PartA/lab_project_2_partA.sim/sim_1/behav/xsim/baud_controller_tb.vcd
$date
   Mon Nov 11 02:12:06 2024
$end

$version
  2024.1
  $dumpfile ("baud_controller_tb.vcd") 
$end

$timescale
  1ps
$end

$scope module baud_controller_tb $end
$var reg 1 ! clk $end
$var reg 1 " reset $end
$var reg 1 # EN $end
$var reg 3 $ baud_select [2:0] $end
$var wire 1 % sample_ENABLE $end
$scope module baud_controller_bench $end
$var wire 1 & clk $end
$var wire 1 ' reset $end
$var wire 3 ( baud_select [2:0] $end
$var wire 1 ) Tx_EN $end
$var reg 1 * sample_ENABLE $end
$var reg 15 + counter [14:0] $end
$var reg 15 , countMax [14:0] $end
$upscope $end
$upscope $end
$enddefinitions $end

#0
$dumpvars
0!
1"
1#
b111 $
0%
0&
1'
b111 (
1)
0*
b0 +
b110110 ,
$end

#5000
1!
1&

#10000
0!
0&

#15000
1!
1&

#20000
0!
0&

#25000
1!
0"
1&
0'
b1 +

#30000
0!
0&

#35000
1!
1&
b10 +

#40000
0!
0&

#45000
1!
1&
b11 +

#50000
0!
0&

#55000
1!
1&
b100 +

#60000
0!
0&

#65000
1!
1&
b101 +

#70000
0!
0&

#75000
1!
1&
b110 +

#80000
0!
0&

#85000
1!
1&
b111 +

#90000
0!
0&

#95000
1!
1&
b1000 +

#100000
0!
0&

#105000
1!
1&
b1001 +

#110000
0!
0&

#115000
1!
1&
b1010 +

#120000
0!
0&

#125000
1!
1&
b1011 +

#130000
0!
0&

#135000
1!
1&
b1100 +

#140000
0!
0&

#145000
1!
1&
b1101 +

#150000
0!
0&

#155000
1!
1&
b1110 +

#160000
0!
0&

#165000
1!
1&
b1111 +

#170000
0!
0&

#175000
1!
1&
b10000 +

#180000
0!
0&

#185000
1!
1&
b10001 +

#190000
0!
0&

#195000
1!
1&
b10010 +

#200000
0!
0&

#205000
1!
1&
b10011 +

#210000
0!
0&

#215000
1!
1&
b10100 +

#220000
0!
0&

#225000
1!
1&
b10101 +

#230000
0!
0&

#235000
1!
1&
b10110 +

#240000
0!
0&

#245000
1!
1&
b10111 +

#250000
0!
0&

#255000
1!
1&
b11000 +

#260000
0!
0&

#265000
1!
1&
b11001 +

#270000
0!
0&

#275000
1!
1&
b11010 +

#280000
0!
0&

#285000
1!
1&
b11011 +

#290000
0!
0&

#295000
1!
1&
b11100 +

#300000
0!
0&

#305000
1!
1&
b11101 +

#310000
0!
0&

#315000
1!
1&
b11110 +

#320000
0!
0&

#325000
1!
1&
b11111 +

#330000
0!
0&

#335000
1!
1&
b100000 +

#340000
0!
0&

#345000
1!
1&
b100001 +

#350000
0!
0&

#355000
1!
1&
b100010 +

#360000
0!
0&

#365000
1!
1&
b100011 +

#370000
0!
0&

#375000
1!
1&
b100100 +

#380000
0!
0&

#385000
1!
1&
b100101 +

#390000
0!
0&

#395000
1!
1&
b100110 +

#400000
0!
0&

#405000
1!
1&
b100111 +

#410000
0!
0&

#415000
1!
1&
b101000 +

#420000
0!
0&

#425000
1!
1&
b101001 +

#430000
0!
0&

#435000
1!
1&
b101010 +

#440000
0!
0&

#445000
1!
1&
b101011 +

#450000
0!
0&

#455000
1!
1&
b101100 +

#460000
0!
0&

#465000
1!
1&
b101101 +

#470000
0!
0&

#475000
1!
1&
b101110 +

#480000
0!
0&

#485000
1!
1&
b101111 +

#490000
0!
0&

#495000
1!
1&
b110000 +

#500000
0!
0&

#505000
1!
1&
b110001 +

#510000
0!
0&

#515000
1!
1&
b110010 +

#520000
0!
0&

#525000
1!
1&
b110011 +

#530000
0!
0&

#535000
1!
1&
b110100 +

#540000
0!
0&

#545000
1!
1&
b110101 +

#550000
0!
0&

#555000
1!
1&
b110110 +

#560000
0!
0&

#565000
1!
1%
1&
1*
b0 +

#570000
0!
0&

#575000
1!
0%
1&
0*
b1 +

#580000
0!
0&

#585000
1!
1&
b10 +

#590000
0!
0&

#595000
1!
1&
b11 +

#600000
0!
0&

#605000
1!
1&
b100 +

#610000
0!
0&

#615000
1!
1&
b101 +

#620000
0!
0&

#625000
1!
1&
b110 +

#630000
0!
0&

#635000
1!
1&
b111 +

#640000
0!
0&

#645000
1!
1&
b1000 +

#650000
0!
0&

#655000
1!
1&
b1001 +

#660000
0!
0&

#665000
1!
1&
b1010 +

#670000
0!
0&

#675000
1!
1&
b1011 +

#680000
0!
0&

#685000
1!
1&
b1100 +

#690000
0!
0&

#695000
1!
1&
b1101 +

#700000
0!
0&

#705000
1!
1&
b1110 +

#710000
0!
0&

#715000
1!
1&
b1111 +

#720000
0!
0&

#725000
1!
1&
b10000 +

#730000
0!
0&

#735000
1!
1&
b10001 +

#740000
0!
0&

#745000
1!
1&
b10010 +

#750000
0!
0&

#755000
1!
1&
b10011 +

#760000
0!
0&

#765000
1!
1&
b10100 +

#770000
0!
0&

#775000
1!
1&
b10101 +

#780000
0!
0&

#785000
1!
1&
b10110 +

#790000
0!
0&

#795000
1!
1&
b10111 +

#800000
0!
0&

#805000
1!
1&
b11000 +

#810000
0!
0&

#815000
1!
1&
b11001 +

#820000
0!
0&

#825000
1!
1&
b11010 +

#830000
0!
0&

#835000
1!
1&
b11011 +

#840000
0!
0&

#845000
1!
1&
b11100 +

#850000
0!
0&

#855000
1!
1&
b11101 +

#860000
0!
0&

#865000
1!
1&
b11110 +

#870000
0!
0&

#875000
1!
1&
b11111 +

#880000
0!
0&

#885000
1!
1&
b100000 +

#890000
0!
0&

#895000
1!
1&
b100001 +

#900000
0!
0&

#905000
1!
1&
b100010 +

#910000
0!
0&

#915000
1!
1&
b100011 +

#920000
0!
0&

#925000
1!
1&
b100100 +

#930000
0!
0&

#935000
1!
1&
b100101 +

#940000
0!
0&

#945000
1!
1&
b100110 +

#950000
0!
0&

#955000
1!
1&
b100111 +

#960000
0!
0&

#965000
1!
1&
b101000 +

#970000
0!
0&

#975000
1!
1&
b101001 +

#980000
0!
0&

#985000
1!
1&
b101010 +

#990000
0!
0&

#995000
1!
1&
b101011 +

#1000000
0!
0&

#1005000
1!
1&
b101100 +

#1010000
0!
0&

#1015000
1!
1&
b101101 +

#1020000
0!
0&

#1025000
1!
1&
b101110 +

#1030000
0!
0&

#1035000
1!
1&
b101111 +

#1040000
0!
0&

#1045000
1!
1&
b110000 +

#1050000
0!
0&

#1055000
1!
1&
b110001 +

#1060000
0!
0&

#1065000
1!
1&
b110010 +

#1070000
0!
0&

#1075000
1!
1&
b110011 +

#1080000
0!
0&

#1085000
1!
1&
b110100 +

#1090000
0!
0&

#1095000
1!
1&
b110101 +

#1100000
0!
0&

#1105000
1!
1&
b110110 +

#1110000
0!
0&

#1115000
1!
1%
1&
1*
b0 +

#1120000
0!
0&

#1125000
1!
0%
1&
0*
b1 +

#1130000
0!
0&

#1135000
1!
1&
b10 +

#1140000
0!
0&

#1145000
1!
1&
b11 +

#1150000
0!
0&

#1155000
1!
1&
b100 +

#1160000
0!
0&

#1165000
1!
1&
b101 +

#1170000
0!
0&

#1175000
1!
1&
b110 +

#1180000
0!
0&

#1185000
1!
1&
b111 +

#1190000
0!
0&

#1195000
1!
1&
b1000 +

#1200000
0!
0&

#1205000
1!
1&
b1001 +

#1210000
0!
0&

#1215000
1!
1&
b1010 +

#1220000
0!
0&

#1225000
1!
1&
b1011 +

#1230000
0!
0&

#1235000
1!
1&
b1100 +

#1240000
0!
0&

#1245000
1!
1&
b1101 +

#1250000
0!
0&

#1255000
1!
1&
b1110 +

#1260000
0!
0&

#1265000
1!
1&
b1111 +

#1270000
0!
0&

#1275000
1!
1&
b10000 +

#1280000
0!
0&

#1285000
1!
1&
b10001 +

#1290000
0!
0&

#1295000
1!
1&
b10010 +

#1300000
0!
0&

#1305000
1!
1&
b10011 +

#1310000
0!
0&

#1315000
1!
1&
b10100 +

#1320000
0!
0&

#1325000
1!
1&
b10101 +

#1330000
0!
0&

#1335000
1!
1&
b10110 +

#1340000
0!
0&

#1345000
1!
1&
b10111 +

#1350000
0!
0&

#1355000
1!
1&
b11000 +

#1360000
0!
0&

#1365000
1!
1&
b11001 +

#1370000
0!
0&

#1375000
1!
1&
b11010 +

#1380000
0!
0&

#1385000
1!
1&
b11011 +

#1390000
0!
0&

#1395000
1!
1&
b11100 +

#1400000
0!
0&

#1405000
1!
1&
b11101 +

#1410000
0!
0&

#1415000
1!
1&
b11110 +

#1420000
0!
0&

#1425000
1!
1&
b11111 +

#1430000
0!
0&

#1435000
1!
1&
b100000 +

#1440000
0!
0&

#1445000
1!
1&
b100001 +

#1450000
0!
0&

#1455000
1!
1&
b100010 +

#1460000
0!
0&

#1465000
1!
1&
b100011 +

#1470000
0!
0&

#1475000
1!
1&
b100100 +

#1480000
0!
0&

#1485000
1!
1&
b100101 +

#1490000
0!
0&

#1495000
1!
1&
b100110 +

#1500000
0!
0&

#1505000
1!
1&
b100111 +

#1510000
0!
0&

#1515000
1!
1&
b101000 +

#1520000
0!
0&

#1525000
1!
1&
b101001 +

#1530000
0!
0&

#1535000
1!
1&
b101010 +

#1540000
0!
0&

#1545000
1!
1&
b101011 +

#1550000
0!
0&

#1555000
1!
1&
b101100 +

#1560000
0!
0&

#1565000
1!
1&
b101101 +

#1570000
0!
0&

#1575000
1!
1&
b101110 +

#1580000
0!
0&

#1585000
1!
1&
b101111 +

#1590000
0!
0&

#1595000
1!
1&
b110000 +

#1600000
0!
0&

#1605000
1!
1&
b110001 +

#1610000
0!
0&

#1615000
1!
1&
b110010 +

#1620000
0!
0&

#1625000
1!
1&
b110011 +

#1630000
0!
0&

#1635000
1!
1&
b110100 +

#1640000
0!
0&

#1645000
1!
1&
b110101 +

#1650000
0!
0&

#1655000
1!
1&
b110110 +

#1660000
0!
0&

#1665000
1!
1%
1&
1*
b0 +

#1670000
0!
0&

#1675000
1!
0%
1&
0*
b1 +

#1680000
0!
0&

#1685000
1!
1&
b10 +

#1690000
0!
0&

#1695000
1!
1&
b11 +

#1700000
0!
0&

#1705000
1!
1&
b100 +

#1710000
0!
0&

#1715000
1!
1&
b101 +

#1720000
0!
0&

#1725000
1!
1&
b110 +

#1730000
0!
0&

#1735000
1!
1&
b111 +

#1740000
0!
0&

#1745000
1!
1&
b1000 +

#1750000
0!
0&

#1755000
1!
1&
b1001 +

#1760000
0!
0&

#1765000
1!
1&
b1010 +

#1770000
0!
0&

#1775000
1!
1&
b1011 +

#1780000
0!
0&

#1785000
1!
1&
b1100 +

#1790000
0!
0&

#1795000
1!
1&
b1101 +

#1800000
0!
0&

#1805000
1!
1&
b1110 +

#1810000
0!
0&

#1815000
1!
1&
b1111 +

#1820000
0!
0&

#1825000
1!
1&
b10000 +

#1830000
0!
0&

#1835000
1!
1&
b10001 +

#1840000
0!
0&

#1845000
1!
1&
b10010 +

#1850000
0!
0&

#1855000
1!
1&
b10011 +

#1860000
0!
0&

#1865000
1!
1&
b10100 +

#1870000
0!
0&

#1875000
1!
1&
b10101 +

#1880000
0!
0&

#1885000
1!
1&
b10110 +

#1890000
0!
0&

#1895000
1!
1&
b10111 +

#1900000
0!
0&

#1905000
1!
1&
b11000 +

#1910000
0!
0&

#1915000
1!
1&
b11001 +

#1920000
0!
0&

#1925000
1!
1&
b11010 +

#1930000
0!
0&

#1935000
1!
1&
b11011 +

#1940000
0!
0&

#1945000
1!
1&
b11100 +

#1950000
0!
0&

#1955000
1!
1&
b11101 +

#1960000
0!
0&

#1965000
1!
1&
b11110 +

#1970000
0!
0&

#1975000
1!
1&
b11111 +

#1980000
0!
0&

#1985000
1!
1&
b100000 +

#1990000
0!
0&

#1995000
1!
1&
b100001 +

#2000000
0!
0&

#2005000
1!
1&
b100010 +

#2010000
0!
0&

#2015000
1!
1&
b100011 +

#2020000
0!
0&

#2025000
1!
1&
b100100 +

#2030000
0!
0&

#2035000
1!
1&
b100101 +

#2040000
0!
0&

#2045000
1!
1&
b100110 +

#2050000
0!
0&

#2055000
1!
1&
b100111 +

#2060000
0!
0&

#2065000
1!
1&
b101000 +

#2070000
0!
0&

#2075000
1!
1&
b101001 +

#2080000
0!
0&

#2085000
1!
1&
b101010 +

#2090000
0!
0&

#2095000
1!
1&
b101011 +

#2100000
0!
0&

#2105000
1!
1&
b101100 +

#2110000
0!
0&

#2115000
1!
1&
b101101 +

#2120000
0!
0&

#2125000
1!
1&
b101110 +

#2130000
0!
0&

#2135000
1!
1&
b101111 +

#2140000
0!
0&

#2145000
1!
1&
b110000 +

#2150000
0!
0&

#2155000
1!
1&
b110001 +

#2160000
0!
0&

#2165000
1!
1&
b110010 +

#2170000
0!
0&

#2175000
1!
1&
b110011 +

#2180000
0!
0&

#2185000
1!
1&
b110100 +

#2190000
0!
0&

#2195000
1!
1&
b110101 +

#2200000
0!
0&

#2205000
1!
1&
b110110 +

#2210000
0!
0&

#2215000
1!
1%
1&
1*
b0 +

#2220000
0!
0&

#2225000
1!
0%
1&
0*
b1 +

#2230000
0!
0&

#2235000
1!
1&
b10 +

#2240000
0!
0&

#2245000
1!
1&
b11 +

#2250000
0!
0&

#2255000
1!
1&
b100 +

#2260000
0!
0&

#2265000
1!
1&
b101 +

#2270000
0!
0&

#2275000
1!
1&
b110 +

#2280000
0!
0&

#2285000
1!
1&
b111 +

#2290000
0!
0&

#2295000
1!
1&
b1000 +

#2300000
0!
0&

#2305000
1!
1&
b1001 +

#2310000
0!
0&

#2315000
1!
1&
b1010 +

#2320000
0!
0&

#2325000
1!
1&
b1011 +

#2330000
0!
0&

#2335000
1!
1&
b1100 +

#2340000
0!
0&

#2345000
1!
1&
b1101 +

#2350000
0!
0&

#2355000
1!
1&
b1110 +

#2360000
0!
0&

#2365000
1!
1&
b1111 +

#2370000
0!
0&

#2375000
1!
1&
b10000 +

#2380000
0!
0&

#2385000
1!
1&
b10001 +

#2390000
0!
0&

#2395000
1!
1&
b10010 +

#2400000
0!
0&

#2405000
1!
1&
b10011 +

#2410000
0!
0&

#2415000
1!
1&
b10100 +

#2420000
0!
0&

#2425000
1!
1&
b10101 +

#2430000
0!
0&

#2435000
1!
1&
b10110 +

#2440000
0!
0&

#2445000
1!
1&
b10111 +

#2450000
0!
0&

#2455000
1!
1&
b11000 +

#2460000
0!
0&

#2465000
1!
1&
b11001 +

#2470000
0!
0&

#2475000
1!
1&
b11010 +

#2480000
0!
0&

#2485000
1!
1&
b11011 +

#2490000
0!
0&

#2495000
1!
1&
b11100 +

#2500000
0!
0&

#2505000
1!
1&
b11101 +

#2510000
0!
0&

#2515000
1!
1&
b11110 +

#2520000
0!
0&

#2525000
1!
1&
b11111 +

#2530000
0!
0&

#2535000
1!
1&
b100000 +

#2540000
0!
0&

#2545000
1!
1&
b100001 +

#2550000
0!
0&

#2555000
1!
1&
b100010 +

#2560000
0!
0&

#2565000
1!
1&
b100011 +

#2570000
0!
0&

#2575000
1!
1&
b100100 +

#2580000
0!
0&

#2585000
1!
1&
b100101 +

#2590000
0!
0&

#2595000
1!
1&
b100110 +

#2600000
0!
0&

#2605000
1!
1&
b100111 +

#2610000
0!
0&

#2615000
1!
1&
b101000 +

#2620000
0!
0&

#2625000
1!
1&
b101001 +

#2630000
0!
0&

#2635000
1!
1&
b101010 +

#2640000
0!
0&

#2645000
1!
1&
b101011 +

#2650000
0!
0&

#2655000
1!
1&
b101100 +

#2660000
0!
0&

#2665000
1!
1&
b101101 +

#2670000
0!
0&

#2675000
1!
1&
b101110 +

#2680000
0!
0&

#2685000
1!
1&
b101111 +

#2690000
0!
0&

#2695000
1!
1&
b110000 +

#2700000
0!
0&

#2705000
1!
1&
b110001 +

#2710000
0!
0&

#2715000
1!
1&
b110010 +

#2720000
0!
0&

#2725000
1!
1&
b110011 +

#2730000
0!
0&

#2735000
1!
1&
b110100 +

#2740000
0!
0&

#2745000
1!
1&
b110101 +

#2750000
0!
0&

#2755000
1!
1&
b110110 +

#2760000
0!
0&

#2765000
1!
1%
1&
1*
b0 +

#2770000
0!
0&

#2775000
1!
0%
1&
0*
b1 +

#2780000
0!
0&

#2785000
1!
1&
b10 +

#2790000
0!
0&

#2795000
1!
1&
b11 +

#2800000
0!
0&

#2805000
1!
1&
b100 +

#2810000
0!
0&

#2815000
1!
1&
b101 +

#2820000
0!
0&

#2825000
1!
1&
b110 +

#2830000
0!
0&

#2835000
1!
1&
b111 +

#2840000
0!
0&

#2845000
1!
1&
b1000 +

#2850000
0!
0&

#2855000
1!
1&
b1001 +

#2860000
0!
0&

#2865000
1!
1&
b1010 +

#2870000
0!
0&

#2875000
1!
1&
b1011 +

#2880000
0!
0&

#2885000
1!
1&
b1100 +

#2890000
0!
0&

#2895000
1!
1&
b1101 +

#2900000
0!
0&

#2905000
1!
1&
b1110 +

#2910000
0!
0&

#2915000
1!
1&
b1111 +

#2920000
0!
0&

#2925000
1!
1&
b10000 +

#2930000
0!
0&

#2935000
1!
1&
b10001 +

#2940000
0!
0&

#2945000
1!
1&
b10010 +

#2950000
0!
0&

#2955000
1!
1&
b10011 +

#2960000
0!
0&

#2965000
1!
1&
b10100 +

#2970000
0!
0&

#2975000
1!
1&
b10101 +

#2980000
0!
0&

#2985000
1!
1&
b10110 +

#2990000
0!
0&

#2995000
1!
1&
b10111 +

#3000000
0!
b110 $
0&
b110 (
b1101101 ,

#3005000
1!
1"
1&
1'
b0 +

#3010000
0!
0&

#3015000
1!
1&

#3020000
0!
0&

#3025000
1!
0"
1&
0'
b1 +

#3030000
0!
0&

#3035000
1!
1&
b10 +

#3040000
0!
0&

#3045000
1!
1&
b11 +

#3050000
0!
0&

#3055000
1!
1&
b100 +

#3060000
0!
0&

#3065000
1!
1&
b101 +

#3070000
0!
0&

#3075000
1!
1&
b110 +

#3080000
0!
0&

#3085000
1!
1&
b111 +

#3090000
0!
0&

#3095000
1!
1&
b1000 +

#3100000
0!
0&

#3105000
1!
1&
b1001 +

#3110000
0!
0&

#3115000
1!
1&
b1010 +

#3120000
0!
0&

#3125000
1!
1&
b1011 +

#3130000
0!
0&

#3135000
1!
1&
b1100 +

#3140000
0!
0&

#3145000
1!
1&
b1101 +

#3150000
0!
0&

#3155000
1!
1&
b1110 +

#3160000
0!
0&

#3165000
1!
1&
b1111 +

#3170000
0!
0&

#3175000
1!
1&
b10000 +

#3180000
0!
0&

#3185000
1!
1&
b10001 +

#3190000
0!
0&

#3195000
1!
1&
b10010 +

#3200000
0!
0&

#3205000
1!
1&
b10011 +

#3210000
0!
0&

#3215000
1!
1&
b10100 +

#3220000
0!
0&

#3225000
1!
1&
b10101 +

#3230000
0!
0&

#3235000
1!
1&
b10110 +

#3240000
0!
0&

#3245000
1!
1&
b10111 +

#3250000
0!
0&

#3255000
1!
1&
b11000 +

#3260000
0!
0&

#3265000
1!
1&
b11001 +

#3270000
0!
0&

#3275000
1!
1&
b11010 +

#3280000
0!
0&

#3285000
1!
1&
b11011 +

#3290000
0!
0&

#3295000
1!
1&
b11100 +

#3300000
0!
0&

#3305000
1!
1&
b11101 +

#3310000
0!
0&

#3315000
1!
1&
b11110 +

#3320000
0!
0&

#3325000
1!
1&
b11111 +

#3330000
0!
0&

#3335000
1!
1&
b100000 +

#3340000
0!
0&

#3345000
1!
1&
b100001 +

#3350000
0!
0&

#3355000
1!
1&
b100010 +

#3360000
0!
0&

#3365000
1!
1&
b100011 +

#3370000
0!
0&

#3375000
1!
1&
b100100 +

#3380000
0!
0&

#3385000
1!
1&
b100101 +

#3390000
0!
0&

#3395000
1!
1&
b100110 +

#3400000
0!
0&

#3405000
1!
1&
b100111 +

#3410000
0!
0&

#3415000
1!
1&
b101000 +

#3420000
0!
0&

#3425000
1!
1&
b101001 +

#3430000
0!
0&

#3435000
1!
1&
b101010 +

#3440000
0!
0&

#3445000
1!
1&
b101011 +

#3450000
0!
0&

#3455000
1!
1&
b101100 +

#3460000
0!
0&

#3465000
1!
1&
b101101 +

#3470000
0!
0&

#3475000
1!
1&
b101110 +

#3480000
0!
0&

#3485000
1!
1&
b101111 +

#3490000
0!
0&

#3495000
1!
1&
b110000 +

#3500000
0!
0&

#3505000
1!
1&
b110001 +

#3510000
0!
0&

#3515000
1!
1&
b110010 +

#3520000
0!
0&

#3525000
1!
1&
b110011 +

#3530000
0!
0&

#3535000
1!
1&
b110100 +

#3540000
0!
0&

#3545000
1!
1&
b110101 +

#3550000
0!
0&

#3555000
1!
1&
b110110 +

#3560000
0!
0&

#3565000
1!
1&
b110111 +

#3570000
0!
0&

#3575000
1!
1&
b111000 +

#3580000
0!
0&

#3585000
1!
1&
b111001 +

#3590000
0!
0&

#3595000
1!
1&
b111010 +

#3600000
0!
0&

#3605000
1!
1&
b111011 +

#3610000
0!
0&

#3615000
1!
1&
b111100 +

#3620000
0!
0&

#3625000
1!
1&
b111101 +

#3630000
0!
0&

#3635000
1!
1&
b111110 +

#3640000
0!
0&

#3645000
1!
1&
b111111 +

#3650000
0!
0&

#3655000
1!
1&
b1000000 +

#3660000
0!
0&

#3665000
1!
1&
b1000001 +

#3670000
0!
0&

#3675000
1!
1&
b1000010 +

#3680000
0!
0&

#3685000
1!
1&
b1000011 +

#3690000
0!
0&

#3695000
1!
1&
b1000100 +

#3700000
0!
0&

#3705000
1!
1&
b1000101 +

#3710000
0!
0&

#3715000
1!
1&
b1000110 +

#3720000
0!
0&

#3725000
1!
1&
b1000111 +

#3730000
0!
0&

#3735000
1!
1&
b1001000 +

#3740000
0!
0&

#3745000
1!
1&
b1001001 +

#3750000
0!
0&

#3755000
1!
1&
b1001010 +

#3760000
0!
0&

#3765000
1!
1&
b1001011 +

#3770000
0!
0&

#3775000
1!
1&
b1001100 +

#3780000
0!
0&

#3785000
1!
1&
b1001101 +

#3790000
0!
0&

#3795000
1!
1&
b1001110 +

#3800000
0!
0&

#3805000
1!
1&
b1001111 +

#3810000
0!
0&

#3815000
1!
1&
b1010000 +

#3820000
0!
0&

#3825000
1!
1&
b1010001 +

#3830000
0!
0&

#3835000
1!
1&
b1010010 +

#3840000
0!
0&

#3845000
1!
1&
b1010011 +

#3850000
0!
0&

#3855000
1!
1&
b1010100 +

#3860000
0!
0&

#3865000
1!
1&
b1010101 +

#3870000
0!
0&

#3875000
1!
1&
b1010110 +

#3880000
0!
0&

#3885000
1!
1&
b1010111 +

#3890000
0!
0&

#3895000
1!
1&
b1011000 +

#3900000
0!
0&

#3905000
1!
1&
b1011001 +

#3910000
0!
0&

#3915000
1!
1&
b1011010 +

#3920000
0!
0&

#3925000
1!
1&
b1011011 +

#3930000
0!
0&

#3935000
1!
1&
b1011100 +

#3940000
0!
0&

#3945000
1!
1&
b1011101 +

#3950000
0!
0&

#3955000
1!
1&
b1011110 +

#3960000
0!
0&

#3965000
1!
1&
b1011111 +

#3970000
0!
0&

#3975000
1!
1&
b1100000 +

#3980000
0!
0&

#3985000
1!
1&
b1100001 +

#3990000
0!
0&

#3995000
1!
1&
b1100010 +

#4000000
0!
0&

#4005000
1!
1&
b1100011 +

#4010000
0!
0&

#4015000
1!
1&
b1100100 +

#4020000
0!
0&

#4025000
1!
1&
b1100101 +

#4030000
0!
0&

#4035000
1!
1&
b1100110 +

#4040000
0!
0&

#4045000
1!
1&
b1100111 +

#4050000
0!
0&

#4055000
1!
1&
b1101000 +

#4060000
0!
0&

#4065000
1!
1&
b1101001 +

#4070000
0!
0&

#4075000
1!
1&
b1101010 +

#4080000
0!
0&

#4085000
1!
1&
b1101011 +

#4090000
0!
0&

#4095000
1!
1&
b1101100 +

#4100000
0!
0&

#4105000
1!
1&
b1101101 +

#4110000
0!
0&

#4115000
1!
1%
1&
1*
b0 +

#4120000
0!
0&

#4125000
1!
0%
1&
0*
b1 +

#4130000
0!
0&

#4135000
1!
1&
b10 +

#4140000
0!
0&

#4145000
1!
1&
b11 +

#4150000
0!
0&

#4155000
1!
1&
b100 +

#4160000
0!
0&

#4165000
1!
1&
b101 +

#4170000
0!
0&

#4175000
1!
1&
b110 +

#4180000
0!
0&

#4185000
1!
1&
b111 +

#4190000
0!
0&

#4195000
1!
1&
b1000 +

#4200000
0!
0&

#4205000
1!
1&
b1001 +

#4210000
0!
0&

#4215000
1!
1&
b1010 +

#4220000
0!
0&

#4225000
1!
1&
b1011 +

#4230000
0!
0&

#4235000
1!
1&
b1100 +

#4240000
0!
0&

#4245000
1!
1&
b1101 +

#4250000
0!
0&

#4255000
1!
1&
b1110 +

#4260000
0!
0&

#4265000
1!
1&
b1111 +

#4270000
0!
0&

#4275000
1!
1&
b10000 +

#4280000
0!
0&

#4285000
1!
1&
b10001 +

#4290000
0!
0&

#4295000
1!
1&
b10010 +

#4300000
0!
0&

#4305000
1!
1&
b10011 +

#4310000
0!
0&

#4315000
1!
1&
b10100 +

#4320000
0!
0&

#4325000
1!
1&
b10101 +

#4330000
0!
0&

#4335000
1!
1&
b10110 +

#4340000
0!
0&

#4345000
1!
1&
b10111 +

#4350000
0!
0&

#4355000
1!
1&
b11000 +

#4360000
0!
0&

#4365000
1!
1&
b11001 +

#4370000
0!
0&

#4375000
1!
1&
b11010 +

#4380000
0!
0&

#4385000
1!
1&
b11011 +

#4390000
0!
0&

#4395000
1!
1&
b11100 +

#4400000
0!
0&

#4405000
1!
1&
b11101 +

#4410000
0!
0&

#4415000
1!
1&
b11110 +

#4420000
0!
0&

#4425000
1!
1&
b11111 +

#4430000
0!
0&

#4435000
1!
1&
b100000 +

#4440000
0!
0&

#4445000
1!
1&
b100001 +

#4450000
0!
0&

#4455000
1!
1&
b100010 +

#4460000
0!
0&

#4465000
1!
1&
b100011 +

#4470000
0!
0&

#4475000
1!
1&
b100100 +

#4480000
0!
0&

#4485000
1!
1&
b100101 +

#4490000
0!
0&

#4495000
1!
1&
b100110 +

#4500000
0!
0&

#4505000
1!
1&
b100111 +

#4510000
0!
0&

#4515000
1!
1&
b101000 +

#4520000
0!
0&

#4525000
1!
1&
b101001 +

#4530000
0!
0&

#4535000
1!
1&
b101010 +

#4540000
0!
0&

#4545000
1!
1&
b101011 +

#4550000
0!
0&

#4555000
1!
1&
b101100 +

#4560000
0!
0&

#4565000
1!
1&
b101101 +

#4570000
0!
0&

#4575000
1!
1&
b101110 +

#4580000
0!
0&

#4585000
1!
1&
b101111 +

#4590000
0!
0&

#4595000
1!
1&
b110000 +

#4600000
0!
0&

#4605000
1!
1&
b110001 +

#4610000
0!
0&

#4615000
1!
1&
b110010 +

#4620000
0!
0&

#4625000
1!
1&
b110011 +

#4630000
0!
0&

#4635000
1!
1&
b110100 +

#4640000
0!
0&

#4645000
1!
1&
b110101 +

#4650000
0!
0&

#4655000
1!
1&
b110110 +

#4660000
0!
0&

